wrattler_python_service/__init__.py
wrattler_python_service/exceptions.py
wrattler_python_service/python_service.py
wrattler_python_service/python_service_utils.py
wrattler_python_service-0.7.dist-info/DESCRIPTION.rst
wrattler_python_service-0.7.dist-info/METADATA
wrattler_python_service-0.7.dist-info/RECORD
wrattler_python_service-0.7.dist-info/WHEEL
wrattler_python_service-0.7.dist-info/entry_points.txt
wrattler_python_service-0.7.dist-info/metadata.json
wrattler_python_service-0.7.dist-info/top_level.txt
