Metadata-Version: 2.0
Name: wrattler-python-service
Version: 0.7
Summary: Python language service for the Wrattler notebook project
Home-page: https://github.com/wrattler/wrattler
Author: Nick Barlow, Tomas Petricek, May Yong
Author-email: UNKNOWN
License: MIT
Platform: UNKNOWN
Requires-Dist: numpy
Requires-Dist: pandas
Requires-Dist: requests
Requires-Dist: flask
Requires-Dist: flask-cors
Requires-Dist: matplotlib
Requires-Dist: scipy
Requires-Dist: pip
Requires-Dist: pyarrow
Requires-Dist: ipython
